digdem/__init__.py
digdem/download_data.py
digdem/gis.py
digdem/plot.py
digdem/section.py
digdem/surfmod.py
digdem-0.2.5.dist-info/LICENSE
digdem-0.2.5.dist-info/METADATA
digdem-0.2.5.dist-info/WHEEL
digdem-0.2.5.dist-info/top_level.txt
digdem-0.2.5.dist-info/RECORD
