Metadata-Version: 2.2
Name: digdem
Version: 0.2.5
Summary: Semi-automated modification of Digital Elevation Models
Author-email: Marc Peruzzetto <m.peruzzetto@brgm.fr>
License: MIT License
Project-URL: Homepage, https://github.com/marcperuz/digdem
Keywords: dem,surface,interpolation,modification
Classifier: License :: OSI Approved :: MIT License
Classifier: Programming Language :: Python
Classifier: Programming Language :: Python :: 3
Requires-Python: >=3.8
License-File: LICENSE
Requires-Dist: shapely
Requires-Dist: geopandas
Requires-Dist: requests
Requires-Dist: scipy
Requires-Dist: matplotlib
Requires-Dist: rasterio
Provides-Extra: test
Requires-Dist: pytest; extra == "test"
Provides-Extra: dev
Requires-Dist: pipreqs; extra == "dev"
